django_sqs/__init__.py
django_sqs/aws_helper.py
django_sqs/aws_services.py
django_sqs/parse_message.py
django_sqs/runtime_config.py
django_sqs/utils.py
django_sqs/launcher/__init__.py
"django_sqs,-/__init__.py"
"django_sqs,-/aws_services.py"
"django_sqs,-/parse_message.py"
"django_sqs,-/runtime_config.py"
"django_sqs,-/utils.py"
"django_sqs,-/launcher/__init__.py"
django_sqs_mq-0.0.4.dist-info/LICENSE
django_sqs_mq-0.0.4.dist-info/METADATA
django_sqs_mq-0.0.4.dist-info/WHEEL
django_sqs_mq-0.0.4.dist-info/top_level.txt
django_sqs_mq-0.0.4.dist-info/zip-safe
django_sqs_mq-0.0.4.dist-info/RECORD
