Metadata-Version: 2.1
Name: django-sqs-mq
Version: 0.0.4
Summary: A simple wrapper for boto3 for receive, and sending, to an AWS SQS queue.
Home-page: https://github.com/firestarry/django-sqs.git
Author: whj
Author-email: whj@linuxbs.com
License: MIT
Platform: UNKNOWN
Classifier: Development Status :: 4 - Beta
Classifier: Intended Audience :: Developers
Classifier: Programming Language :: Python :: 3
Classifier: License :: OSI Approved :: MIT License
Classifier: Operating System :: OS Independent
Requires-Python: >=3.6
Requires-Dist: django (>=1.11.29)
Requires-Dist: boto3 (>=1.12.33)
